torchchronos/__init__.py
torchchronos/datasets/__init__.py
torchchronos/datasets/tfc_pretrain.py
torchchronos/datasets/ucr_uea.py
torchchronos/download.py
torchchronos/errors.py
torchchronos/lightning/__init__.py
torchchronos/lightning/tfc_pretrain.py
torchchronos/lightning/ucr_uea.py
torchchronos/transforms/__init__.py
torchchronos/transforms/base.py
torchchronos/transforms/padding.py
torchchronos/typing.py
torchchronos/utils.py
torchchronos-0.0.4.dist-info/LICENSE
torchchronos-0.0.4.dist-info/METADATA
torchchronos-0.0.4.dist-info/WHEEL
torchchronos-0.0.4.dist-info/RECORD
