Metadata-Version: 2.1
Name: torchchronos
Version: 0.0.4
Summary: PyTorch and Lightning compatible library that provides easy and flexible access to various time-series datasets for classification and regression tasks
Home-page: https://github.com/mauricekraus/torchchronos
License: MIT
Author: Maurice Kraus
Author-email: dev@mkraus.io
Requires-Python: >=3.10,<3.12
Classifier: License :: OSI Approved :: MIT License
Classifier: Programming Language :: Python :: 3
Classifier: Programming Language :: Python :: 3.10
Classifier: Programming Language :: Python :: 3.11
Requires-Dist: fastapi (>=0.88.0,<0.89.0)
Requires-Dist: lightning (>=2.0.0,<3.0.0)
Requires-Dist: sktime (>=0.16.1,<0.17.0)
Requires-Dist: torch (>=2.0.0,!=2.0.1)
Requires-Dist: uplink (>=0.9.7,<0.10.0)
